srcml_caller/__init__.py
srcml_caller/__init__.pyi
srcml_caller/_srcml_caller.cpython-310-x86_64-linux-gnu.so
srcml_caller/py.typed
srcml_caller/include/srcml.h
srcml_caller/lib64/libsrcml.a
srcml_caller/lib64/libsrcml.so
srcml_caller/lib64/libsrcml.so.1
srcml_caller/lib64/libsrcml.so.1.0.0
srcml_caller/share/cmake/srcml/srcML-shared-targets-release.cmake
srcml_caller/share/cmake/srcml/srcML-shared-targets.cmake
srcml_caller/share/cmake/srcml/srcML-static-targets-release.cmake
srcml_caller/share/cmake/srcml/srcML-static-targets.cmake
srcml_caller/share/cmake/srcml/srcMLConfig.cmake
srcml_caller/share/cmake/srcml/srcMLConfigVersion.cmake
srcml_caller.libs/libexslt-4062d795.so.0.8.17
srcml_caller.libs/libgcrypt-18957bae.so.11.8.2
srcml_caller.libs/libgpg-error-3f09c3c7.so.0.10.0
srcml_caller.libs/liblzma-004595ca.so.5.2.2
srcml_caller.libs/libxml2-3998bec4.so.2.9.1
srcml_caller.libs/libxslt-c37b94dc.so.1.1.28
srcml_caller-0.4.0.dist-info/METADATA
srcml_caller-0.4.0.dist-info/WHEEL
srcml_caller-0.4.0.dist-info/top_level.txt
srcml_caller-0.4.0.dist-info/RECORD
srcml_caller-0.4.0.dist-info/licenses/COPYING.txt
