Metadata-Version: 2.4
Name: srcml-caller
Version: 0.4.0
Summary: srcml_caller, simple python bindings for srcML 
Home-page: https://github.com/pthom/srcml_caller
Author: Pascal Thomet
Author-email: pthomet@gmail.com
Requires-Python: >=3.6
License-File: COPYING.txt
Provides-Extra: test
Requires-Dist: pytest; extra == "test"
Dynamic: author
Dynamic: author-email
Dynamic: description
Dynamic: description-content-type
Dynamic: home-page
Dynamic: license-file
Dynamic: provides-extra
Dynamic: requires-python
Dynamic: summary
